fwq/__init__.py
fwq/api.py
fwq/broker.py
fwq/cli.py
fwq/constants.py
fwq/logs.py
fwq/version.txt
fwq/work_q.py
fwq/worker.py
fwq/aws/__init__.py
fwq/jobs/__init__.py
fwq-25.3.10.dist-info/licenses/LICENSE
fwq-25.3.10.dist-info/METADATA
fwq-25.3.10.dist-info/WHEEL
fwq-25.3.10.dist-info/entry_points.txt
fwq-25.3.10.dist-info/top_level.txt
fwq-25.3.10.dist-info/RECORD
