Metadata-Version: 2.4
Name: fwq
Version: 25.3.10
Author-email: Ron Glasmann <ron@glasmann.net>
License: MIT
License-File: LICENSE
Requires-Dist: gwerks>=25.3.17
Requires-Dist: pyyaml
Requires-Dist: greenstalk
Provides-Extra: aws
Requires-Dist: boto3; extra == "aws"
Dynamic: license-file
